d2_widget/__init__.py
d2_widget/_model.py
d2_widget/_utils.py
d2_widget/_version.py
d2_widget/_widget.py
d2_widget/static/widget.css
d2_widget/static/widget.js
d2_widget-0.0.3.dist-info/METADATA
d2_widget-0.0.3.dist-info/WHEEL
d2_widget-0.0.3.dist-info/licenses/LICENSE
d2_widget-0.0.3.dist-info/RECORD
