Metadata-Version: 2.4
Name: d2-widget
Version: 0.0.3
Summary: An AnyWidget for displaying declarative diagrams written in D2
Project-URL: Homepage, https://github.com/peter-gy/d2-widget
Project-URL: Repository, https://github.com/peter-gy/d2-widget
Project-URL: Documentation, https://github.com/peter-gy/d2-widget#readme
Project-URL: Bug Tracker, https://github.com/peter-gy/d2-widget/issues
Author-email: Péter Ferenc Gyarmati <dev.petergy@gmail.com>
License: Copyright © 2025 Péter Ferenc Gyarmati
License-File: LICENSE
Keywords: anywidget,d2,diagram,jupyter,widget
Classifier: Development Status :: 4 - Beta
Classifier: Framework :: Jupyter
Classifier: Intended Audience :: Developers
Classifier: Intended Audience :: Science/Research
Classifier: License :: OSI Approved :: MIT License
Classifier: Programming Language :: Python
Classifier: Programming Language :: Python :: 3
Classifier: Programming Language :: Python :: 3.9
Classifier: Programming Language :: Python :: 3.10
Classifier: Programming Language :: Python :: 3.11
Classifier: Programming Language :: Python :: 3.12
Classifier: Programming Language :: Python :: 3.13
Requires-Python: >=3.9
Requires-Dist: anywidget>=0.9
Requires-Dist: traitlets>=5
